stackstore/__init__.py
stackstore/admin.py
stackstore/apps.py
stackstore/models.py
django_stackstore_model_ooppyy-1.0.dist-info/AUTHORS.md
django_stackstore_model_ooppyy-1.0.dist-info/LICENSE
django_stackstore_model_ooppyy-1.0.dist-info/METADATA
django_stackstore_model_ooppyy-1.0.dist-info/WHEEL
django_stackstore_model_ooppyy-1.0.dist-info/top_level.txt
django_stackstore_model_ooppyy-1.0.dist-info/RECORD
