Metadata-Version: 2.1
Name: django-stackstore-model-ooppyy
Version: 1.0
Summary: Django stackstore model
Home-page: https://github.com/c2emarket-ooppyy/django-stackstore-model
Author: OoppyY
Keywords: django,model,versioning
Classifier: Development Status :: 5 - Production/Stable
Classifier: Environment :: Web Environment
Classifier: Framework :: Django
Classifier: Intended Audience :: Developers
Classifier: License :: OSI Approved :: MIT License
Classifier: Operating System :: OS Independent
Classifier: Programming Language :: Python
Classifier: Programming Language :: Python :: 3
Classifier: Topic :: Internet :: WWW/HTTP
Classifier: Topic :: Internet :: WWW/HTTP :: Dynamic Content
License-File: LICENSE
License-File: AUTHORS.md
